{
  "routes": [
    {
      "method": "GET",
      "path": "/testusers",
      "handler": "Testuser.find",
      "config": {
        "policies": []
      }
    },
    {
      "method": "GET",
      "path": "/testusers/count",
      "handler": "Testuser.count",
      "config": {
        "policies": []
      }
    },
    {
      "method": "GET",
      "path": "/testusers/:id",
      "handler": "Testuser.findOne",
      "config": {
        "policies": []
      }
    },
    {
      "method": "POST",
      "path": "/testusers",
      "handler": "Testuser.create",
      "config": {
        "policies": []
      }
    },
    {
      "method": "PUT",
      "path": "/testusers/:id",
      "handler": "Testuser.update",
      "config": {
        "policies": []
      }
    },
    {
      "method": "DELETE",
      "path": "/testusers/:id",
      "handler": "Testuser.destroy",
      "config": {
        "policies": []
      }
    }
  ]
}
